{
  "title": "The Decoder Ring",
  "tier": 3,
  "description": "Movie comprehension layer. Demonstratives, commands, street slang, and emotional exclamations. The final key to understanding Tamil media.",
  "episodes": [
    {
      "episode": 1,
      "topic": "This & That",
      "intro": "Demonstratives. Like this. Like that. This one. That one. Same thing. Different thing. The words that point at reality.",
      "vocab": [
        {
          "tamil": "அப்படி",
          "english": "Like that"
        },
        {
          "tamil": "இப்படி",
          "english": "Like this"
        },
        {
          "tamil": "அந்த",
          "english": "That (adjective)"
        },
        {
          "tamil": "இந்த",
          "english": "This (adjective)"
        },
        {
          "tamil": "அதே",
          "english": "Same / That same"
        },
        {
          "tamil": "வேற",
          "english": "Other / Different / Else"
        }
      ],
      "scenario": "'Do it like this, not like that'. 'That shop, not this one'. 'Same place as yesterday?'. 'No, different street'. The six words that organize all of reality into this vs. that."
    },
    {
      "episode": 2,
      "topic": "Commands & Warnings",
      "intro": "Movie commands. Look! Listen! Be careful! Stop! Run! The informal imperative that drives every action scene.",
      "vocab": [
        {
          "tamil": "பாரு",
          "english": "Look! (informal)"
        },
        {
          "tamil": "கேளு",
          "english": "Listen! (informal)"
        },
        {
          "tamil": "ஜாக்கிரதை",
          "english": "Careful! / Watch out!"
        },
        {
          "tamil": "நில்லு",
          "english": "Stop! / Stand! (informal)"
        },
        {
          "tamil": "ஓடு",
          "english": "Run! (informal)"
        }
      ],
      "scenario": "Action movie vocab. 'Look out!' 'Listen to me!' 'Be careful!' 'Stop right there!' 'Run!'. The five commands that drive every Tamil movie climax."
    },
    {
      "episode": 3,
      "topic": "Street Talk",
      "intro": "The informal register. The slang you hear between friends, in movies, and on the street. Use with care.",
      "vocab": [
        {
          "tamil": "போடா",
          "english": "Get lost! / Go! (informal, male)"
        },
        {
          "tamil": "போடி",
          "english": "Get lost! / Go! (informal, female)"
        },
        {
          "tamil": "கலக்குறே",
          "english": "You're killing it / Rocking"
        },
        {
          "tamil": "mass",
          "english": "Mass / Powerful / Impressive (slang)"
        }
      ],
      "scenario": "Friends at a cricket match. 'Dhoni is mass!'. 'You're killing it!'. Rival fan trash talks. 'Get lost!'. Understanding the register. When to use it (friends). When to NEVER use it (elders)."
    },
    {
      "episode": 4,
      "topic": "Emotional Peaks",
      "intro": "The exclamations that punctuate every Tamil movie climax. Wow. Oh god. Tsk. Why like this? Pure emotion in sound.",
      "vocab": [
        {
          "tamil": "ஆஹா",
          "english": "Wow / Ah (wonder)"
        },
        {
          "tamil": "சே",
          "english": "Tsk / Disappointment"
        },
        {
          "tamil": "கடவுளே",
          "english": "Oh God!"
        },
        {
          "tamil": "ஏன் இப்படி?",
          "english": "Why like this?"
        }
      ],
      "scenario": "Movie climax. Hero discovers the truth. 'Oh God!'. 'Why like this?'. Beautiful sunset. 'Wow!'. Plan goes wrong. 'Tsk'. The emotional punctuation of Tamil storytelling."
    },
    {
      "episode": 5,
      "topic": "BOSS FIGHT: The Movie Scene",
      "intro": "A full movie scene described to you. Decode every word. Identify commands, emotions, demonstratives, and slang.",
      "vocab": [],
      "scenario": "Hero enters. 'Look at this!' He shows something. 'That same person!' Villain appears. 'Stop!' 'Run!' 'Be careful!' 'Oh God, why like this?'. Friend says 'You're mass, go!' Hero turns around. 'Listen, I won't run'. Decode everything."
    },
    {
      "episode": 6,
      "topic": "Rest and Reps",
      "intro": "Audit Day. Movie vocabulary: demonstratives, commands, slang, exclamations.",
      "vocab": [
        {
          "tamil": "அப்படி",
          "english": "Like that"
        },
        {
          "tamil": "இப்படி",
          "english": "Like this"
        },
        {
          "tamil": "பாரு",
          "english": "Look"
        },
        {
          "tamil": "ஜாக்கிரதை",
          "english": "Careful"
        },
        {
          "tamil": "கலக்குறே",
          "english": "Killing it"
        },
        {
          "tamil": "கடவுளே",
          "english": "Oh God"
        }
      ],
      "scenario": "Rapid fire. I play a movie moment. You identify the word category: command, emotion, demonstrative, or slang."
    },
    {
      "episode": 7,
      "topic": "Your First Tamil Movie Guide",
      "intro": "You have the vocabulary. Now use it. Which movie to watch first. How to use subtitles strategically. What to listen for. Your graduation mission.",
      "vocab": [
        {
          "tamil": "படம்",
          "english": "Movie / Film"
        },
        {
          "tamil": "பாட்டு",
          "english": "Song"
        },
        {
          "tamil": "கதை",
          "english": "Story"
        }
      ],
      "scenario": "Your first Tamil movie watch plan. Start with a comedy (easier dialogue). Watch with English subtitles first. Then Tamil subtitles. Then nothing. Listen for the words you know. The movie becomes your teacher. You have arrived."
    }
  ]
}